CriminAI/MANIFEST.in
CriminAI/__init__.py
CriminAI/conf.py
CriminAI/interface.py
CriminAI/vae_model.pth
CriminAI/AlgoGenetique/AlgorithmeGénétique.md
CriminAI/AlgoGenetique/__init__.py
CriminAI/AlgoGenetique/algo_genetique.py
CriminAI/VAE/AlgorithmeVAE.md
CriminAI/VAE/__init__.py
CriminAI/VAE/autoencodeur_BW.py
CriminAI/VAE/olivetti_py3.pkz
CriminAI/VAE/image_batch/000001.jpg
CriminAI/VAE/image_batch/000002.jpg
CriminAI/VAE/image_batch/000003.jpg
CriminAI/VAE/image_batch/000004.jpg
CriminAI/VAE/image_batch/000005.jpg
CriminAI/VAE/image_batch/000006.jpg
CriminAI/VAE/image_batch/000007.jpg
CriminAI/VAE/image_batch/000008.jpg
CriminAI/VAE/image_batch/000009.jpg
CriminAI/VAE/image_batch/000010.jpg
CriminAI/VAE/image_batch/000011.jpg
CriminAI/VAE/image_batch/000012.jpg
CriminAI/VAE/image_batch/000013.jpg
CriminAI/VAE/image_batch/000014.jpg
CriminAI/VAE/image_batch/000015.jpg
CriminAI/VAE/image_batch/000016.jpg
CriminAI/VAE/image_batch/000017.jpg
CriminAI/VAE/image_batch/000018.jpg
CriminAI/VAE/image_batch/000019.jpg
CriminAI/VAE/image_batch/000020.jpg
CriminAI/VAE/image_batch/000021.jpg
CriminAI/VAE/image_batch/000022.jpg
CriminAI/VAE/image_batch/000023.jpg
CriminAI/VAE/image_batch/000024.jpg
CriminAI/VAE/image_batch/000025.jpg
CriminAI/VAE/image_batch/000026.jpg
CriminAI/VAE/image_batch/000027.jpg
CriminAI/VAE/image_batch/000028.jpg
CriminAI/VAE/image_batch/000029.jpg
CriminAI/VAE/image_batch/000030.jpg
CriminAI/VAE/image_batch/000031.jpg
CriminAI/VAE/image_batch/000032.jpg
CriminAI/VAE/image_batch/000033.jpg
CriminAI/VAE/image_batch/000034.jpg
CriminAI/VAE/image_batch/000035.jpg
CriminAI/VAE/image_batch/000036.jpg
CriminAI/VAE/image_batch/000037.jpg
CriminAI/VAE/image_batch/000038.jpg
CriminAI/VAE/image_batch/000039.jpg
CriminAI/VAE/image_batch/000040.jpg
CriminAI/VAE/image_batch/000041.jpg
CriminAI/VAE/image_batch/000042.jpg
CriminAI/VAE/image_batch/000043.jpg
CriminAI/VAE/image_batch/000044.jpg
CriminAI/VAE/image_batch/000045.jpg
CriminAI/VAE/image_batch/000046.jpg
CriminAI-1.0.6.dist-info/LICENSE.txt
CriminAI-1.0.6.dist-info/METADATA
CriminAI-1.0.6.dist-info/WHEEL
CriminAI-1.0.6.dist-info/entry_points.txt
CriminAI-1.0.6.dist-info/top_level.txt
CriminAI-1.0.6.dist-info/RECORD
