Metadata-Version: 2.1
Name: CriminAI
Version: 1.0.6
Summary: CriminAI est un logiciel de génération de portraits robots par IA
Author-email: ZOUARI Matis <matis.zouari@insa-lyon.fr>, SUTTER Clémence <clemence.sutter@insa-lyon.fr>, PEREZ Lisa <lisa.perez@insa-lyon.fr>, ZHONG Zhihan <zhihan.zhong@insa-lyon.fr>
License: MIT License
Project-URL: Repository, https://github.com/matzouari/CriminAI
Classifier: Development Status :: 4 - Beta
Classifier: Intended Audience :: Developers
Classifier: Topic :: Software Development :: Build Tools
Classifier: Programming Language :: Python :: 3
Requires-Python: >=3
License-File: LICENSE.txt
Requires-Dist: numpy >=1.11.1
Requires-Dist: matplotlib >=3.0.0
Requires-Dist: torch ==2.0.1
Requires-Dist: torchvision
Requires-Dist: tk
Requires-Dist: pillow
Requires-Dist: scikit-learn
